README.md
setup.cfg
setup.py
distributions_trial/Binomialdistribution.py
distributions_trial/Gaussiandistribution.py
distributions_trial/Generaldistribution.py
distributions_trial/__init__.py
distributions_trial.egg-info/PKG-INFO
distributions_trial.egg-info/SOURCES.txt
distributions_trial.egg-info/dependency_links.txt
distributions_trial.egg-info/not-zip-safe
distributions_trial.egg-info/top_level.txt